pydeezer/Deezer.py
pydeezer/Downloader.py
pydeezer/ProgressHandler.py
pydeezer/__init__.py
pydeezer/cli.py
pydeezer/exceptions.py
pydeezer/util.py
pydeezer/constants/__init__.py
pydeezer/constants/api_methods.py
pydeezer/constants/api_urls.py
pydeezer/constants/image_hosts.py
pydeezer/constants/networking_settings.py
pydeezer/constants/search_types.py
pydeezer/constants/track_formats.py
py_deezer-1.1.4.post1.dist-info/LICENSE
py_deezer-1.1.4.post1.dist-info/METADATA
py_deezer-1.1.4.post1.dist-info/WHEEL
py_deezer-1.1.4.post1.dist-info/entry_points.txt
py_deezer-1.1.4.post1.dist-info/top_level.txt
py_deezer-1.1.4.post1.dist-info/RECORD
