Metadata-Version: 2.1
Name: py-deezer
Version: 1.1.4.post1
Summary: A package to search and download musics on Deezer
Home-page: https://github.com/Chr1st-oo/pydeezer
Author: Aaron Gonzales
Author-email: aaroncgonzales.dev@gmail.com
License: GNU GPL v3
Platform: UNKNOWN
Classifier: Programming Language :: Python :: 3
Classifier: Operating System :: OS Independent
Requires-Dist: requests
Requires-Dist: cryptography
Requires-Dist: mutagen
Requires-Dist: rich
Requires-Dist: click
Requires-Dist: pyinquirer
Requires-Dist: colorama
